exportevernote/EverNote.py
exportevernote/__init__.py
evernote_export-1.0.2.dist-info/LICENSE
evernote_export-1.0.2.dist-info/METADATA
evernote_export-1.0.2.dist-info/WHEEL
evernote_export-1.0.2.dist-info/entry_points.txt
evernote_export-1.0.2.dist-info/top_level.txt
evernote_export-1.0.2.dist-info/RECORD
