Metadata-Version: 2.1
Name: evernote-export
Version: 1.0.2
Summary: 批量导出Evernote中的所有笔记，按照笔记目录，存档到本地对应文件夹
Home-page: https://github.com/dong-s/ExportAllEverNote
Author: Dong
Author-email: dong@dong-s.com
License: MIT
Keywords: evernote export enex
Platform: UNKNOWN
Classifier: Development Status :: 3 - Alpha
Classifier: Intended Audience :: Developers
Classifier: Topic :: Software Development :: Libraries :: Python Modules
Classifier: License :: OSI Approved :: MIT License
Classifier: Programming Language :: Python :: 2.7
Requires-Dist: evernote
